pyramid_traversal_api/__init__.py
pyramid_traversal_api/cors.py
pyramid_traversal_api/crud.py
pyramid_traversal_api/deprecation.py
pyramid_traversal_api/openapi/__init__.py
pyramid_traversal_api/openapi/generator.py
pyramid_traversal_api/openapi/helpers.py
pyramid_traversal_api/sunset.py
pyramid_traversal_api/traversal_node/.coverage
pyramid_traversal_api/traversal_node/__init__.py
pyramid_traversal_api/traversal_node/collection.py
pyramid_traversal_api/traversal_node/sqla_collection.py
pyramid_traversal_api-0.4.0.dist-info/licenses/LICENSE
pyramid_traversal_api-0.4.0.dist-info/WHEEL
pyramid_traversal_api-0.4.0.dist-info/METADATA
pyramid_traversal_api-0.4.0.dist-info/RECORD
