Metadata-Version: 2.4
Name: pyramid_traversal_api
Version: 0.4.0
Summary: Tools for writing REST APIs in Pyramid using the traversal API
License-Expression: MIT
License-File: LICENSE
Classifier: Development Status :: 3 - Alpha
Classifier: Framework :: Pyramid
Classifier: Intended Audience :: Developers
Classifier: Programming Language :: Python :: 3
Classifier: Operating System :: OS Independent
Requires-Dist: marshmallow
Requires-Dist: pyramid
Requires-Dist: apispec
Requires-Dist: pyyaml>=6.0.3
Requires-Dist: ruff ; extra == 'dev'
Requires-Dist: sphinx ; extra == 'dev'
Requires-Dist: pytest ; extra == 'dev'
Requires-Dist: pytest-cov ; extra == 'dev'
Requires-Dist: pytest-mock ; extra == 'dev'
Requires-Dist: webtest>=3.0.7 ; extra == 'dev'
Requires-Dist: sqlalchemy ; extra == 'sqla'
Requires-Python: >=3.10
Provides-Extra: dev
Provides-Extra: sqla
